{
    "Number of label 3 in the final training set": 6131,
    "Number of label 4 in the final training set (after downsampling)": 306,
    "Number of label 3 in the final test set": 1010,
    "Number of label 4 in the final test set": 982,
    "Total samples in final training set": 6437,
    "Total samples in final test set": 1992,
    "Number of batches in training set": 101,
    "Number of batches in test set": 32,
    "TP": 582,
    "FP": 44,
    "FN": 428,
    "TN": 938,
    "Accuracy": 0.7631,
    "Misclassification rate": 0.2369,
    "Sensitivity (Recall)": 0.5762,
    "Specificity": 0.9552,
    "Precision": 0.9297,
    "Negative Predictive Value": 0.6867,
    "G-mean": 0.7419,
    "F-measure": 0.7115,
    "Discriminant Power (DP)": 1.8563,
    "F2-measure": 0.8281,
    "InvF0.5-measure": 0.6237,
    "AGF": 0.7187,
    "Balanced Accuracy": 0.7657,
    "Matthew's Correlation Coefficient (MCC)": 0.5723,
    "Cohen's Kappa": 0.5286,
    "Youden's Index": 0.5314,
    "Positive Likelihood Ratio (LR+)": 12.8606,
    "Negative Likelihood Ratio (LR-)": 0.4436
}