{
    "Number of label 3 in the final training set": 6000,
    "Number of label 4 in the final training set (after downsampling)": 120,
    "Number of label 3 in the final test set": 1000,
    "Number of label 4 in the final test set": 1000,
    "Total samples in final training set": 6120,
    "Total samples in final test set": 2000,
    "Number of batches in training set": 96,
    "Number of batches in test set": 32,
    "TP": 523,
    "FP": 43,
    "FN": 477,
    "TN": 957,
    "Accuracy": 0.74,
    "Misclassification rate": 0.26,
    "Sensitivity (Recall)": 0.523,
    "Specificity": 0.957,
    "Precision": 0.924,
    "Negative Predictive Value": 0.6674,
    "G-mean": 0.7075,
    "F-measure": 0.6679,
    "Discriminant Power (DP)": 1.7613,
    "F2-measure": 0.8012,
    "InvF0.5-measure": 0.5727,
    "AGF": 0.6774,
    "Balanced Accuracy": 0.74,
    "Matthew's Correlation Coefficient (MCC)": 0.5328,
    "Cohen's Kappa": 0.48,
    "Youden's Index": 0.48,
    "Positive Likelihood Ratio (LR+)": 12.1628,
    "Negative Likelihood Ratio (LR-)": 0.4984
}