{
    "Number of label 3 in the final training set": 5000,
    "Number of label 4 in the final training set (after downsampling)": 1000,
    "Number of label 3 in the final test set": 1000,
    "Number of label 4 in the final test set": 1000,
    "Total samples in final training set": 6000,
    "Total samples in final test set": 2000,
    "Number of batches in training set": 94,
    "Number of batches in test set": 32,
    "TP": 321,
    "FP": 36,
    "FN": 679,
    "TN": 964,
    "Accuracy": 0.6425,
    "Misclassification rate": 0.3575,
    "Sensitivity (Recall)": 0.321,
    "Specificity": 0.964,
    "Precision": 0.8992,
    "Negative Predictive Value": 0.5867,
    "G-mean": 0.5563,
    "F-measure": 0.4731,
    "Discriminant Power (DP)": 1.3995,
    "F2-measure": 0.661,
    "InvF0.5-measure": 0.3684,
    "AGF": 0.4935,
    "Balanced Accuracy": 0.6425,
    "Matthew's Correlation Coefficient (MCC)": 0.3721,
    "Cohen's Kappa": 0.285,
    "Youden's Index": 0.285,
    "Positive Likelihood Ratio (LR+)": 8.9167,
    "Negative Likelihood Ratio (LR-)": 0.7044
}