{
    "Number of label 3 in the final training set": 6000,
    "Number of label 4 in the final training set (after downsampling)": 30,
    "Number of label 3 in the final test set": 1000,
    "Number of label 4 in the final test set": 1000,
    "Total samples in final training set": 6030,
    "Total samples in final test set": 2000,
    "Number of batches in training set": 95,
    "Number of batches in test set": 32,
    "TP": 1000,
    "FP": 617,
    "FN": 0,
    "TN": 383,
    "Accuracy": 0.6915,
    "Misclassification rate": 0.3085,
    "Sensitivity (Recall)": 1.0,
    "Specificity": 0.383,
    "Precision": 0.6184,
    "Negative Predictive Value": 1.0,
    "G-mean": 0.6189,
    "F-measure": 0.7642,
    "Discriminant Power (DP)": -999999999,
    "F2-measure": 0.6695,
    "InvF0.5-measure": 0.8902,
    "AGF": 0.772,
    "Balanced Accuracy": 0.6915,
    "Matthew's Correlation Coefficient (MCC)": 0.4867,
    "Cohen's Kappa": 0.383,
    "Youden's Index": 0.383,
    "Positive Likelihood Ratio (LR+)": 1.6207,
    "Negative Likelihood Ratio (LR-)": 0.0
}