{
    "Number of label 3 in the final training set": 5000,
    "Number of label 4 in the final training set (after downsampling)": 25,
    "Number of label 3 in the final test set": 1000,
    "Number of label 4 in the final test set": 1000,
    "Total samples in final training set": 5025,
    "Total samples in final test set": 2000,
    "Number of batches in training set": 79,
    "Number of batches in test set": 32,
    "TP": 998,
    "FP": 996,
    "FN": 2,
    "TN": 4,
    "Accuracy": 0.501,
    "Misclassification rate": 0.499,
    "Sensitivity (Recall)": 0.998,
    "Specificity": 0.004,
    "Precision": 0.5005,
    "Negative Predictive Value": 0.6667,
    "G-mean": 0.0632,
    "F-measure": 0.6667,
    "Discriminant Power (DP)": 0.3833,
    "F2-measure": 0.5559,
    "InvF0.5-measure": 0.8325,
    "AGF": 0.6803,
    "Balanced Accuracy": 0.501,
    "Matthew's Correlation Coefficient (MCC)": 0.0183,
    "Cohen's Kappa": 0.002,
    "Youden's Index": 0.002,
    "Positive Likelihood Ratio (LR+)": 1.002,
    "Negative Likelihood Ratio (LR-)": 0.5
}