{
    "Number of label 3 in the final training set": 6742,
    "Number of label 4 in the final training set (after downsampling)": 674,
    "Number of label 3 in the final test set": 1135,
    "Number of label 4 in the final test set": 1028,
    "Total samples in final training set": 7416,
    "Total samples in final test set": 2163,
    "Number of batches in training set": 116,
    "Number of batches in test set": 34,
    "TP": 1135.0,
    "FP": 10.0,
    "FN": 0.0,
    "TN": 1018.0,
    "Accuracy": 0.9954,
    "Misclassification rate": 0.0046,
    "Sensitivity (Recall)": 1.0,
    "Specificity": 0.9903,
    "Precision": 0.9913,
    "Negative Predictive Value": 1.0,
    "G-mean": 0.9951,
    "F-measure": 0.9956,
    "Discriminant Power (DP)": -999999999,
    "F2-measure": 0.993,
    "InvF0.5-measure": 0.9982,
    "AGF": 0.9956,
    "Balanced Accuracy": 0.9951,
    "Matthew's Correlation Coefficient (MCC)": 0.9908,
    "Cohen's Kappa": 0.9907,
    "Youden's Index": 0.9903,
    "Positive Likelihood Ratio (LR+)": 102.8,
    "Negative Likelihood Ratio (LR-)": 0.0
}